[{"title":"computadora","description":"es gamer","price":"10000","thumbnail":"algo normal","code":"132748848","stock":"2","id":1,"category":"electronica","status":"true"},{"title":"computadora","description":"es gamer","price":"10000","thumbnail":"algo normal","stock":"2","id":2,"category":"electronica","status":"true"},{"title":"computadora2","description":"es gamer","price":"10000","thumbnail":"algo normal","code":"1327488482","stock":"2","id":3,"category":"electronica","status":"true"},{"title":"computadora2","description":"es gamer","price":"10000","thumbnail":"algo normal","stock":"2","id":4,"category":"electronica","status":"true"},{"title":"computadora2","description":"es gamer","price":"10000","thumbnail":"algo normal","stock":"2","id":5,"category":"electronica","status":"true"},{"title":"computadora2","description":"es gamer","price":"10000","thumbnail":"algo normal","stock":"2","id":6,"category":"electronica","status":"true"}]